list_flatten/__init__.py
list_flatten/main.py
list_flatten-0.1.6.dist-info/METADATA
list_flatten-0.1.6.dist-info/WHEEL
list_flatten-0.1.6.dist-info/RECORD
