Metadata-Version: 2.1
Name: list-flatten
Version: 0.1.6
Summary: A simple python package to flatten a list of lists. Works for 2d and 3d lists.
Home-page: https://github.com/SampurnaC/list-flatten
License: MIT
Author: Sampurna Chapagain
Author-email: sampurna.chapagainnn@gmail.com
Requires-Python: >=3.8,<4.0
Classifier: License :: OSI Approved :: MIT License
Classifier: Programming Language :: Python :: 3
Classifier: Programming Language :: Python :: 3.8
Classifier: Programming Language :: Python :: 3.9
Classifier: Programming Language :: Python :: 3.10
Classifier: Programming Language :: Python :: 3.11
Project-URL: Repository, https://github.com/SampurnaC/list-flatten
